iFeatureOmegaGUI/__init__.py
iFeatureOmegaGUI/iFeatureOmegaGUI.py
iFeatureOmegaGUI/data/1A1T.pdb
iFeatureOmegaGUI/data/1iir.pdb
iFeatureOmegaGUI/data/Chemical_SMILES.txt
iFeatureOmegaGUI/data/Chemical_SMILES1.txt
iFeatureOmegaGUI/data/DNA_sequences.txt
iFeatureOmegaGUI/data/PCA.csv
iFeatureOmegaGUI/data/RNA_sequences.txt
iFeatureOmegaGUI/data/data_with_labels.csv
iFeatureOmegaGUI/data/data_without_labels.csv
iFeatureOmegaGUI/data/peptide_sequences.txt
iFeatureOmegaGUI/images/logo.ico
iFeatureOmegaGUI/images/progress_bar.gif
iFeatureOmegaGUI/util/CheckAccPseParameter.py
iFeatureOmegaGUI/util/DataAnalysis.py
iFeatureOmegaGUI/util/InputDialog.py
iFeatureOmegaGUI/util/MCL.py
iFeatureOmegaGUI/util/PlotWidgets.py
iFeatureOmegaGUI/util/StructureVisualizationWidget.py
iFeatureOmegaGUI/util/TableWidget.py
iFeatureOmegaGUI/util/__init__.py
iFeatureOmegaGUI/util/iChemical.py
iFeatureOmegaGUI/util/iSequence.py
iFeatureOmegaGUI/util/iStructure.py
iFeatureOmegaGUI/util/chem/AtomProperty.py
iFeatureOmegaGUI/util/chem/AtomTypes.py
iFeatureOmegaGUI/util/chem/__init__.py
iFeatureOmegaGUI/util/chem/autocor.py
iFeatureOmegaGUI/util/chem/basak.py
iFeatureOmegaGUI/util/chem/burden.py
iFeatureOmegaGUI/util/chem/cats.py
iFeatureOmegaGUI/util/chem/charge.py
iFeatureOmegaGUI/util/chem/connectivity.py
iFeatureOmegaGUI/util/chem/constitution.py
iFeatureOmegaGUI/util/chem/estate.py
iFeatureOmegaGUI/util/chem/fingerprint.py
iFeatureOmegaGUI/util/chem/fingerprint_old.py
iFeatureOmegaGUI/util/chem/kappa.py
iFeatureOmegaGUI/util/chem/property.py
iFeatureOmegaGUI/util/chem/topology.py
iFeatureOmegaGUI/util/data/AAidx.txt
iFeatureOmegaGUI/util/data/AAindex.data
iFeatureOmegaGUI/util/data/AAindex.txt
iFeatureOmegaGUI/util/data/CTD.txt
iFeatureOmegaGUI/util/data/DPCP.data
iFeatureOmegaGUI/util/data/DPCP.txt
iFeatureOmegaGUI/util/data/Grantham.txt
iFeatureOmegaGUI/util/data/PAAC.txt
iFeatureOmegaGUI/util/data/PCPsD.data
iFeatureOmegaGUI/util/data/PCPsD.txt
iFeatureOmegaGUI/util/data/Schneider-Wrede.txt
iFeatureOmegaGUI-1.0.5.dist-info/METADATA
iFeatureOmegaGUI-1.0.5.dist-info/WHEEL
iFeatureOmegaGUI-1.0.5.dist-info/top_level.txt
iFeatureOmegaGUI-1.0.5.dist-info/RECORD
