Metadata-Version: 2.1
Name: iFeatureOmegaGUI
Version: 1.0.5
Summary: An integrative platform for the prediction/feature engineering, visualization and analysis of features from molecular sequence, structural and ligand data sets
Home-page: https://github.com/Superzchen/iFeatureOmega-GUI
Author: SuperZhen
Author-email: chenzhen-win2009@163.com
License: MIT License
Keywords: iFeatureOmegaGUI
Platform: any
Requires-Dist: qdarkstyle
Requires-Dist: sip
Requires-Dist: datetime
Requires-Dist: networkx
Requires-Dist: numpy (>=1.21.4)
Requires-Dist: pandas (>=1.3.4)
Requires-Dist: scikit-learn (>=1.0.1)
Requires-Dist: scipy (>=1.7.3)
Requires-Dist: matplotlib (==3.4.3)
Requires-Dist: seaborn
Requires-Dist: joblib
